nzbget/Database.py
nzbget/FeedScript.py
nzbget/Logger.py
nzbget/PostProcessCommon.py
nzbget/PostProcessScript.py
nzbget/QueueScript.py
nzbget/SABPostProcessScript.py
nzbget/ScanScript.py
nzbget/SchedulerScript.py
nzbget/ScriptBase.py
nzbget/Utils.py
nzbget/__init__.py
pynzbget-0.6.4.dist-info/LICENSE
pynzbget-0.6.4.dist-info/METADATA
pynzbget-0.6.4.dist-info/WHEEL
pynzbget-0.6.4.dist-info/top_level.txt
pynzbget-0.6.4.dist-info/RECORD
