Metadata-Version: 2.1
Name: pynzbget
Version: 0.6.4
Summary: Provides a framework for NZBGet and SABnzbd scriptdevelopment.
Home-page: http://github.com/caronc/pynzbget
Author: Chris Caron
Author-email: lead2gold@gmail.com
License: GPLv3
Keywords: nzbget,postprocess,framework,scripts,nzb,sabnzbd
Platform: UNKNOWN
Classifier: Development Status :: 5 - Production/Stable
Classifier: Intended Audience :: Developers
Classifier: License :: OSI Approved :: GNU General Public License v3 (GPLv3)
Classifier: Operating System :: OS Independent
Classifier: Natural Language :: English
Classifier: Programming Language :: Python
Classifier: Programming Language :: Python :: 2.7
Classifier: Programming Language :: Python :: 3
Classifier: Topic :: Software Development :: Libraries :: Python Modules
Classifier: Topic :: Software Development :: Libraries :: Application Frameworks
Requires: lxml
Requires: sqlite3
Requires-Python: >=2.7
Requires-Dist: lxml (>=2.7)
Requires-Dist: six
